driva_python_sdk/__init__.py
driva_python_sdk/__main__.py
driva_python_sdk/core/__init__.py
driva_python_sdk/core/settings.py
driva_python_sdk/messages/__init__.py
driva_python_sdk/messages/broker.py
driva_python_sdk/messages/connector.py
driva_python_sdk/messages/message.py
driva_python_sdk/py.typed
driva_python_sdk/quality/__init__.py
driva_python_sdk/quality/phone.py
driva_python_sdk-0.5.1.dist-info/entry_points.txt
driva_python_sdk-0.5.1.dist-info/LICENSE.rst
driva_python_sdk-0.5.1.dist-info/WHEEL
driva_python_sdk-0.5.1.dist-info/METADATA
driva_python_sdk-0.5.1.dist-info/RECORD
