Metadata-Version: 2.1
Name: driva-python-sdk
Version: 0.5.1
Summary: Driva Python Sdk
Home-page: https://github.com/victordriva/driva-python-sdk
License: GPL-3.0
Author: Victor Hugo
Author-email: victor@datadriva.com
Requires-Python: >=3.8,<4.0
Classifier: Development Status :: 1 - Planning
Classifier: License :: OSI Approved :: GNU General Public License v3 (GPLv3)
Classifier: Programming Language :: Python :: 3
Classifier: Programming Language :: Python :: 3.10
Classifier: Programming Language :: Python :: 3.8
Classifier: Programming Language :: Python :: 3.9
Requires-Dist: click (>=8.0.1,<9.0.0)
Requires-Dist: kafka-python (>=2.0.2,<3.0.0)
Requires-Dist: pydantic-avro (>=0.2.4,<0.4.0)
Requires-Dist: pydantic[dotenv] (>=1.9.0,<2.0.0)
Requires-Dist: python-schema-registry-client (>=2.2.2,<3.0.0)
Requires-Dist: requests (>=2.27.1,<3.0.0)
Project-URL: Changelog, https://github.com/victordriva/driva-python-sdk/releases
Project-URL: Documentation, https://driva-python-sdk.readthedocs.io
Project-URL: Repository, https://github.com/victordriva/driva-python-sdk
